{
  "Abertamy": [
    12.81826,
    50.36874
  ],
  "Adamov": [
    16.65253,
    49.30162
  ],
  "Albrechtice": [
    18.52444,
    49.78645
  ],
  "Albrechtice nad Orlic\u00ed": [
    16.06437,
    50.13979
  ],
  "A\u0161": [
    12.19499,
    50.22387
  ],
  "Babice": [
    17.48075,
    49.12167
  ],
  "Bakov nad Jizerou": [
    14.94149,
    50.4823
  ],
  "Barto\u0161ovice": [
    18.05461,
    49.66884
  ],
  "Batelov": [
    15.39465,
    49.31425
  ],
  "Bavorov": [
    14.07893,
    49.12184
  ],
  "Ba\u0161ka": [
    18.37233,
    49.64584
  ],
  "Bechl\u00edn": [
    14.34092,
    50.41615
  ],
  "Bechyn\u011b": [
    14.4681,
    49.29523
  ],
  "Bediho\u0161\u0165": [
    17.16643,
    49.44826
  ],
  "Benecko": [
    15.54816,
    50.66633
  ],
  "Bene\u0161ov": [
    14.68697,
    49.78162
  ],
  "Bene\u0161ov nad Plou\u010dnic\u00ed": [
    14.31239,
    50.74159
  ],
  "Bene\u0161ov nad \u010cernou": [
    14.62737,
    48.7294
  ],
  "Ben\u00e1tky nad Jizerou": [
    14.82343,
    50.29085
  ],
  "Bernartice": [
    14.38101,
    49.36889
  ],
  "Beroun": [
    14.072,
    49.96382
  ],
  "Bezdru\u017eice": [
    12.9711,
    49.90724
  ],
  "Be\u010dov": [
    13.71784,
    50.44972
  ],
  "Blansko": [
    16.64446,
    49.36304
  ],
  "Blatn\u00e1": [
    13.88176,
    49.42489
  ],
  "Bla\u017eovice": [
    16.78611,
    49.16569
  ],
  "Blovice": [
    13.54009,
    49.5822
  ],
  "Bludov": [
    16.92849,
    49.9408
  ],
  "Blu\u010dina": [
    16.6445,
    49.05497
  ],
  "Bl\u00ed\u017eejov": [
    12.98926,
    49.5
  ],
  "Bl\u00ed\u017ekovice": [
    15.83482,
    48.99976
  ],
  "Bochov": [
    13.05227,
    50.14872
  ],
  "Bohdalov": [
    15.87582,
    49.47921
  ],
  "Bohum\u00edn": [
    18.35755,
    49.90411
  ],
  "Bohuslavice": [
    18.12866,
    49.94232
  ],
  "Bohut\u00edn": [
    13.94389,
    49.65551
  ],
  "Bohu\u0148ovice": [
    17.28693,
    49.66301
  ],
  "Bohu\u0161ovice nad Oh\u0159\u00ed": [
    14.15048,
    50.49316
  ],
  "Bojkovice": [
    17.81487,
    49.03864
  ],
  "Bolatice": [
    18.08358,
    49.95172
  ],
  "Bor": [
    12.77516,
    49.71159
  ],
  "Borek": [
    14.50088,
    49.02339
  ],
  "Borohr\u00e1dek": [
    16.09326,
    50.09777
  ],
  "Borovany": [
    14.64227,
    48.8986
  ],
  "Borov\u00e1 Lada": [
    13.65986,
    48.98983
  ],
  "Bor\u0161ice": [
    17.35084,
    49.06254
  ],
  "Boskovice": [
    16.65997,
    49.48751
  ],
  "Bouzov": [
    16.89288,
    49.70426
  ],
  "Bo\u0159etice": [
    16.85306,
    48.91302
  ],
  "Bo\u0159itov": [
    16.59119,
    49.42504
  ],
  "Bo\u0161ovice": [
    16.83676,
    49.05351
  ],
  "Bo\u017eice": [
    16.28875,
    48.83687
  ],
  "Brand\u00fds nad Labem-Star\u00e1 Boleslav": [
    14.66326,
    50.18709
  ],
  "Brand\u00fds nad Orlic\u00ed": [
    16.28528,
    50.00194
  ],
  "Brand\u00fdsek": [
    14.16199,
    50.18923
  ],
  "Brantice": [
    17.62911,
    50.06351
  ],
  "Bran\u00edk": [
    14.41235,
    50.03597
  ],
  "Bra\u0148any": [
    13.70017,
    50.54295
  ],
  "Brloh": [
    14.21857,
    48.92987
  ],
  "Brni\u0161t\u011b": [
    14.70338,
    50.72919
  ],
  "Brno": [
    16.60796,
    49.19522
  ],
  "Brn\u011bnec": [
    16.52202,
    49.62735
  ],
  "Brodek u P\u0159erova": [
    17.33825,
    49.48419
  ],
  "Broumov": [
    16.33181,
    50.58566
  ],
  "Brtnice": [
    15.67642,
    49.30695
  ],
  "Brumovice": [
    17.74958,
    50.0153
  ],
  "Brunt\u00e1l": [
    17.4647,
    49.98844
  ],
  "Bru\u0161perk": [
    18.2221,
    49.7001
  ],
  "Buchlovice": [
    17.33852,
    49.08627
  ],
  "Budi\u0161ov": [
    16.00383,
    49.27138
  ],
  "Budi\u0161ov nad Budi\u0161ovkou": [
    17.62969,
    49.79511
  ],
  "Budyn\u011b nad Oh\u0159\u00ed": [
    14.12591,
    50.40427
  ],
  "Bukovany": [
    12.57265,
    50.16632
  ],
  "Bukovec": [
    18.82683,
    49.55114
  ],
  "Bu\u010dovice": [
    17.00191,
    49.14896
  ],
  "Bu\u0161t\u011bhrad": [
    14.18897,
    50.15594
  ],
  "Bystr\u00e9": [
    16.34679,
    49.62846
  ],
  "Byst\u0159any": [
    13.86419,
    50.62867
  ],
  "Byst\u0159ec": [
    16.619,
    50.01168
  ],
  "Byst\u0159ice": [
    18.72038,
    49.63657
  ],
  "Byst\u0159ice nad Pern\u0161tejnem": [
    16.26147,
    49.52295
  ],
  "Byst\u0159ice pod Host\u00fdnem": [
    17.67401,
    49.39924
  ],
  "By\u0161ice": [
    14.61136,
    50.31044
  ],
  "Bzenec": [
    17.26685,
    48.97336
  ],
  "B\u00e1nov": [
    17.71752,
    48.98801
  ],
  "B\u00edlina": [
    13.77535,
    50.54854
  ],
  "B\u00edlina Kyselka": [
    13.76667,
    50.55
  ],
  "B\u00edlovec": [
    18.01581,
    49.75639
  ],
  "B\u00edlovice": [
    17.54961,
    49.09965
  ],
  "B\u00edlovice nad Svitavou": [
    16.67247,
    49.24708
  ],
  "B\u00edl\u00e1 Lhota": [
    16.97507,
    49.70953
  ],
  "B\u00edl\u00e1 T\u0159eme\u0161n\u00e1": [
    15.74101,
    50.44465
  ],
  "B\u00fd\u0161\u0165": [
    15.91116,
    50.13243
  ],
  "B\u011blot\u00edn": [
    17.80654,
    49.5912
  ],
  "B\u011bl\u00e1 nad Radbuzou": [
    12.71761,
    49.59115
  ],
  "B\u011bl\u00e1 pod Bezd\u011bzem": [
    14.80418,
    50.50121
  ],
  "B\u0159asy": [
    13.57833,
    49.837
  ],
  "B\u0159eclav": [
    16.88203,
    48.75897
  ],
  "B\u0159eznice": [
    17.66277,
    49.18643
  ],
  "B\u0159ezno": [
    13.42118,
    50.40185
  ],
  "B\u0159ezolupy": [
    17.58034,
    49.12138
  ],
  "B\u0159ezov\u00e1": [
    17.73986,
    48.92543
  ],
  "B\u0159ezov\u00e1 nad Svitavou": [
    16.51799,
    49.64418
  ],
  "B\u0159ez\u00ed": [
    16.56748,
    48.81928
  ],
  "B\u0159idli\u010dn\u00e1": [
    17.37107,
    49.91167
  ],
  "Cerhenice": [
    15.07203,
    50.07127
  ],
  "Chaba\u0159ovice": [
    13.94184,
    50.67318
  ],
  "Cheb": [
    12.37392,
    50.07963
  ],
  "Chlebi\u010dov": [
    17.96748,
    49.95942
  ],
  "Chlum u T\u0159ebon\u011b": [
    14.92799,
    48.96235
  ],
  "Chlumec": [
    13.93964,
    50.69972
  ],
  "Chlumec nad Cidlinou": [
    15.46026,
    50.1544
  ],
  "Chlum\u010dany": [
    13.31323,
    49.63256
  ],
  "Choce\u0148": [
    16.22303,
    50.00161
  ],
  "Chodov": [
    12.74551,
    50.24018
  ],
  "Chodov\u00e1 Plan\u00e1": [
    12.73014,
    49.89321
  ],
  "Chomutov": [
    13.41779,
    50.46048
  ],
  "Chotoviny": [
    14.67695,
    49.47803
  ],
  "Chot\u011bbo\u0159": [
    15.67018,
    49.72072
  ],
  "Chot\u011bbuz": [
    18.56912,
    49.76849
  ],
  "Chot\u011b\u0161ov": [
    13.20271,
    49.65408
  ],
  "Chrast": [
    15.93396,
    49.90205
  ],
  "Chrastava": [
    14.96884,
    50.81693
  ],
  "Chropyn\u011b": [
    17.36451,
    49.35644
  ],
  "Chroustovice": [
    15.99143,
    49.95553
  ],
  "Chrudim": [
    15.79558,
    49.95109
  ],
  "Chr\u00e1st": [
    13.49358,
    49.7932
  ],
  "Chucheln\u00e1": [
    18.11656,
    49.98664
  ],
  "Chvaletice": [
    15.41846,
    50.03443
  ],
  "Chval\u010dov": [
    17.71149,
    49.38918
  ],
  "Chval\u0161iny": [
    14.21114,
    48.85401
  ],
  "Chy\u0148ava": [
    14.07398,
    50.02736
  ],
  "Chy\u0161ky": [
    14.42757,
    49.52346
  ],
  "Ch\u00fdnov": [
    14.81122,
    49.40677
  ],
  "Ch\u0159ibsk\u00e1": [
    14.48444,
    50.86079
  ],
  "Cvikov": [
    14.63298,
    50.77668
  ],
  "C\u00edrkvice": [
    15.33505,
    49.9456
  ],
  "C\u00edtov": [
    14.39813,
    50.37225
  ],
  "Dalovice": [
    12.89581,
    50.24779
  ],
  "Dambo\u0159ice": [
    16.91757,
    49.03828
  ],
  "Darkovice": [
    18.22213,
    49.93592
  ],
  "Davle": [
    14.40037,
    49.89218
  ],
  "Da\u010dice": [
    15.43727,
    49.08154
  ],
  "Da\u0161ice": [
    15.91244,
    50.02844
  ],
  "Desn\u00e1": [
    15.30284,
    50.75987
  ],
  "Divi\u0161ov": [
    14.87579,
    49.78849
  ],
  "Dlouh\u00e1 T\u0159ebov\u00e1": [
    16.42329,
    49.9404
  ],
  "Dobratice": [
    18.49226,
    49.66039
  ],
  "Dobrom\u011b\u0159ice": [
    13.79473,
    50.37009
  ],
  "Dobron\u00edn": [
    15.64992,
    49.47833
  ],
  "Dobrovice": [
    14.96233,
    50.36933
  ],
  "Dobru\u0161ka": [
    16.16001,
    50.29201
  ],
  "Dobr\u00e1": [
    18.41393,
    49.67383
  ],
  "Dob\u0159any": [
    13.29307,
    49.65482
  ],
  "Dob\u0159ichovice": [
    14.27469,
    49.92749
  ],
  "Dob\u0159\u00edv": [
    13.68681,
    49.71566
  ],
  "Dob\u0159\u00ed\u0161": [
    14.16717,
    49.78113
  ],
  "Dob\u0161ice": [
    16.08218,
    48.84834
  ],
  "Doksy": [
    14.04782,
    50.119
  ],
  "Dolany": [
    17.3224,
    49.64987
  ],
  "Doln\u00ed Bene\u0161ov": [
    18.10835,
    49.92101
  ],
  "Doln\u00ed Be\u010dva": [
    18.19419,
    49.45498
  ],
  "Doln\u00ed Be\u0159kovice": [
    14.45024,
    50.39313
  ],
  "Doln\u00ed Bohd\u00edkov": [
    16.90433,
    50.00996
  ],
  "Doln\u00ed Bojanovice": [
    17.02859,
    48.85861
  ],
  "Doln\u00ed Bousov": [
    15.12812,
    50.43825
  ],
  "Doln\u00ed Bukovsko": [
    14.58127,
    49.17086
  ],
  "Doln\u00ed B\u0159e\u017eany": [
    14.4585,
    49.96321
  ],
  "Doln\u00ed Cerekev": [
    15.45655,
    49.34449
  ],
  "Doln\u00ed Dobrou\u010d": [
    16.49766,
    49.99273
  ],
  "Doln\u00ed Dunajovice": [
    16.59283,
    48.85447
  ],
  "Doln\u00ed Dvo\u0159i\u0161t\u011b": [
    14.45221,
    48.65642
  ],
  "Doln\u00ed Kounice": [
    16.46492,
    49.07011
  ],
  "Doln\u00ed Lhota": [
    18.09241,
    49.84236
  ],
  "Doln\u00ed Libina": [
    17.10729,
    49.85821
  ],
  "Doln\u00ed Lou\u0107ky": [
    16.35871,
    49.36099
  ],
  "Doln\u00ed Lutyn\u011b": [
    18.42815,
    49.89876
  ],
  "Doln\u00ed N\u011bm\u010d\u00ed": [
    17.58585,
    48.96837
  ],
  "Doln\u00ed Podlu\u017e\u00ed": [
    14.59503,
    50.87988
  ],
  "Doln\u00ed Poustevna": [
    14.28684,
    50.98251
  ],
  "Doln\u00ed Po\u010dernice": [
    14.57199,
    50.0876
  ],
  "Doln\u00ed Rove\u0148": [
    15.96774,
    50.02927
  ],
  "Doln\u00ed Rychnov": [
    12.64507,
    50.16462
  ],
  "Doln\u00ed Sloupnice": [
    16.29401,
    49.92721
  ],
  "Doln\u00ed Stud\u00e9nky": [
    16.97107,
    49.93506
  ],
  "Doln\u00ed \u00dajezd": [
    17.53547,
    49.54597
  ],
  "Doln\u00ed \u010cermn\u00e1": [
    16.56475,
    49.97954
  ],
  "Doln\u00ed \u010cernilov": [
    15.96107,
    50.2611
  ],
  "Doln\u00ed \u017dandov": [
    12.55101,
    50.01794
  ],
  "Doln\u00ed \u017divotice": [
    17.77969,
    49.89732
  ],
  "Doloplazy": [
    17.41393,
    49.56876
  ],
  "Doman\u00edn": [
    17.28476,
    49.00167
  ],
  "Doma\u017elice": [
    12.92976,
    49.44049
  ],
  "Doubrava": [
    18.48018,
    49.85873
  ],
  "Doubravice nad Svitavou": [
    16.62937,
    49.43664
  ],
  "Doudleby nad Orlic\u00ed": [
    16.26131,
    50.10742
  ],
  "Drahanovice": [
    17.07701,
    49.57856
  ],
  "Drnholec": [
    16.48586,
    48.85746
  ],
  "Drnovice": [
    16.95146,
    49.2763
  ],
  "Dr\u00e1sov": [
    16.47798,
    49.33183
  ],
  "Dub nad Moravou": [
    17.27723,
    49.48249
  ],
  "Dubicko": [
    16.96266,
    49.82806
  ],
  "Dubn\u00e9": [
    14.36038,
    48.97619
  ],
  "Dub\u00e1": [
    14.54023,
    50.54034
  ],
  "Dub\u00ed": [
    13.78561,
    50.68558
  ],
  "Dub\u0148any": [
    17.09004,
    48.91694
  ],
  "Duchcov": [
    13.74621,
    50.60376
  ],
  "Dvorce": [
    17.54762,
    49.83332
  ],
  "Dv\u016fr Kr\u00e1lov\u00e9 nad Labem": [
    15.81402,
    50.43172
  ],
  "D\u00fd\u0161ina": [
    13.4915,
    49.77735
  ],
  "D\u011btmarovice": [
    18.46079,
    49.89412
  ],
  "D\u011b\u010d\u00edn": [
    14.21478,
    50.78215
  ],
  "D\u0159evohostice": [
    17.59204,
    49.42594
  ],
  "D\u0159ite\u0148": [
    14.34596,
    49.1428
  ],
  "Francova Lhota": [
    18.11175,
    49.20174
  ],
  "Franti\u0161kovy L\u00e1zn\u011b": [
    12.35174,
    50.12033
  ],
  "Fren\u0161t\u00e1t pod Radho\u0161t\u011bm": [
    18.21078,
    49.54835
  ],
  "Frymburk": [
    14.16564,
    48.66094
  ],
  "Fry\u010dovice": [
    18.22321,
    49.66677
  ],
  "Fry\u0161t\u00e1k": [
    17.68346,
    49.2852
  ],
  "Fr\u00fddek-M\u00edstek": [
    18.35,
    49.68333
  ],
  "Fr\u00fddlant": [
    15.07974,
    50.92139
  ],
  "Fr\u00fddlant nad Ostravic\u00ed": [
    18.35967,
    49.5928
  ],
  "Fulnek": [
    17.90319,
    49.71238
  ],
  "Gol\u010d\u016fv Jen\u00edkov": [
    15.47686,
    49.81626
  ],
  "Grygov": [
    17.30887,
    49.53841
  ],
  "Habartov": [
    12.55054,
    50.18297
  ],
  "Habry": [
    15.48486,
    49.75603
  ],
  "Halenkov": [
    18.14749,
    49.3174
  ],
  "Halenkovice": [
    17.47156,
    49.17102
  ],
  "Hanu\u0161ovice": [
    16.93641,
    50.08049
  ],
  "Harrachov": [
    15.43141,
    50.77209
  ],
  "Hartmanice": [
    13.45455,
    49.16948
  ],
  "Havl\u00ed\u010dk\u016fv Brod": [
    15.58069,
    49.60785
  ],
  "Hav\u00ed\u0159ov": [
    18.43688,
    49.77984
  ],
  "Hazlov": [
    12.27238,
    50.15634
  ],
  "Ha\u0165": [
    18.23931,
    49.94644
  ],
  "Hejnice": [
    15.18168,
    50.8772
  ],
  "Her\u00e1lec": [
    15.45708,
    49.53083
  ],
  "Hevl\u00edn": [
    16.38131,
    48.75209
  ],
  "He\u0159manova Hu\u0165": [
    13.10069,
    49.70679
  ],
  "He\u0159man\u016fv M\u011bstec": [
    15.66492,
    49.94707
  ],
  "Hlinsko": [
    15.90756,
    49.76213
  ],
  "Hlohovec": [
    16.7623,
    48.77399
  ],
  "Hlubok\u00e1 nad Vltavou": [
    14.43427,
    49.05225
  ],
  "Hlubo\u010dky": [
    17.39436,
    49.61783
  ],
  "Hluk": [
    17.52668,
    48.98812
  ],
  "Hlu\u010d\u00edn": [
    18.19196,
    49.89795
  ],
  "Hn\u011bvot\u00edn": [
    17.17954,
    49.57205
  ],
  "Hn\u011bvo\u0161ice": [
    18.00829,
    50.00299
  ],
  "Hodkovice nad Mohelkou": [
    15.08985,
    50.66586
  ],
  "Hodkovi\u010dky": [
    14.41741,
    50.02809
  ],
  "Hodonice": [
    16.16337,
    48.8368
  ],
  "Hodon\u00edn": [
    17.13244,
    48.84893
  ],
  "Hodslavice": [
    18.02367,
    49.53856
  ],
  "Holasovice": [
    17.80847,
    49.99843
  ],
  "Hole\u0161ov": [
    17.57832,
    49.33331
  ],
  "Holice": [
    15.9859,
    50.06601
  ],
  "Holoubkov": [
    13.69246,
    49.77598
  ],
  "Hol\u00fd\u0161ov": [
    13.10129,
    49.59361
  ],
  "Hora\u017e\u010fovice": [
    13.701,
    49.32069
  ],
  "Horka nad Moravou": [
    17.2107,
    49.64009
  ],
  "Horn\u00ed Bene\u0161ov": [
    17.60262,
    49.96682
  ],
  "Horn\u00ed Be\u010dva": [
    18.28859,
    49.43216
  ],
  "Horn\u00ed Bludovice": [
    18.43677,
    49.74965
  ],
  "Horn\u00ed Brann\u00e1": [
    15.57146,
    50.60826
  ],
  "Horn\u00ed B\u0159\u00edza": [
    13.35558,
    49.84012
  ],
  "Horn\u00ed Cerekev": [
    15.32769,
    49.32026
  ],
  "Horn\u00ed Jelen\u00ed": [
    16.08396,
    50.04901
  ],
  "Horn\u00ed Ji\u0159et\u00edn": [
    13.54717,
    50.57309
  ],
  "Horn\u00ed Libina": [
    17.07262,
    49.88987
  ],
  "Horn\u00ed Lide\u010d": [
    18.06099,
    49.18121
  ],
  "Horn\u00ed Mo\u0161t\u011bnice": [
    17.45879,
    49.41213
  ],
  "Horn\u00ed M\u011bsto": [
    17.21112,
    49.90845
  ],
  "Horn\u00ed Plan\u00e1": [
    14.03257,
    48.76736
  ],
  "Horn\u00ed Po\u010daply": [
    14.38993,
    50.4244
  ],
  "Horn\u00ed Po\u010dernice": [
    14.61036,
    50.1121
  ],
  "Horn\u00ed Slavkov": [
    12.80758,
    50.13863
  ],
  "Horn\u00ed Sloupnice": [
    16.33948,
    49.92138
  ],
  "Horn\u00ed Stropnice": [
    14.73502,
    48.76124
  ],
  "Horn\u00ed Such\u00e1": [
    18.48189,
    49.7978
  ],
  "Horn\u00ed T\u011brlicko": [
    18.4829,
    49.75177
  ],
  "Horn\u00ed \u010cermn\u00e1": [
    16.60772,
    49.97053
  ],
  "Horn\u00ed \u0160t\u011bp\u00e1nov": [
    16.79078,
    49.54901
  ],
  "Horom\u011b\u0159ice": [
    14.33879,
    50.13173
  ],
  "Hor\u0161ovsk\u00fd T\u00fdn": [
    12.94405,
    49.52965
  ],
  "Hostavice": [
    14.55822,
    50.09283
  ],
  "Hostinn\u00e9": [
    15.72334,
    50.54066
  ],
  "Hostivice": [
    14.25856,
    50.08158
  ],
  "Hostomice": [
    14.0456,
    49.82526
  ],
  "Hostou\u0148": [
    12.77147,
    49.55971
  ],
  "Host\u011bradice": [
    16.25931,
    48.95006
  ],
  "Hovorany": [
    16.99346,
    48.95493
  ],
  "Hovor\u010dovice": [
    14.51789,
    50.17866
  ],
  "Hov\u011bz\u00ed": [
    18.06062,
    49.30365
  ],
  "Ho\u0159ice": [
    15.63183,
    50.36609
  ],
  "Ho\u0159ovice": [
    13.90268,
    49.83597
  ],
  "Ho\u0161\u0165ka": [
    14.335,
    50.48859
  ],
  "Ho\u0161\u0165\u00e1lkov\u00e1": [
    17.86944,
    49.35467
  ],
  "Hrabyn\u011b": [
    18.05483,
    49.88249
  ],
  "Hradec Kr\u00e1lov\u00e9": [
    15.83277,
    50.20923
  ],
  "Hradec nad Moravici": [
    17.87842,
    49.87042
  ],
  "Hradec nad Svitavou": [
    16.48058,
    49.71143
  ],
  "Hradi\u0161\u0165ko": [
    14.40935,
    49.86828
  ],
  "Hranice": [
    17.73469,
    49.54796
  ],
  "Hrd\u011bjovice": [
    14.47857,
    49.01893
  ],
  "Hrob": [
    13.72676,
    50.65919
  ],
  "Hroch\u016fv T\u00fdnec": [
    15.91054,
    49.95946
  ],
  "Hromnice": [
    13.44146,
    49.84907
  ],
  "Hronov": [
    16.1823,
    50.47968
  ],
  "Hrotovice": [
    16.06067,
    49.1077
  ],
  "Hroznov\u00e1 Lhota": [
    17.41697,
    48.90784
  ],
  "Hrozn\u011bt\u00edn": [
    12.8718,
    50.3094
  ],
  "Hru\u0161ky": [
    16.97404,
    48.79272
  ],
  "Hru\u0161ovany nad Jevi\u0161ovkou": [
    16.40271,
    48.82991
  ],
  "Hru\u0161ovany u Brna": [
    16.59429,
    49.03863
  ],
  "Hr\u00e1dek": [
    13.4985,
    49.26127
  ],
  "Hr\u00e1dek nad Nisou": [
    14.84455,
    50.85279
  ],
  "Hudlice": [
    13.97063,
    49.96096
  ],
  "Hukvaldy": [
    18.22189,
    49.62381
  ],
  "Hul\u00edn": [
    17.46374,
    49.31689
  ],
  "Humpolec": [
    15.35932,
    49.54152
  ],
  "Husinec": [
    13.98697,
    49.05496
  ],
  "Hustope\u010de": [
    16.73762,
    48.94085
  ],
  "Hustope\u010de Nad Be\u010dvou": [
    17.86994,
    49.53053
  ],
  "Hvozdn\u00e1": [
    17.75163,
    49.24848
  ],
  "H\u00e1j ve Slezsku": [
    18.0954,
    49.89856
  ],
  "H\u00fdskov": [
    14.05055,
    49.99072
  ],
  "H\u0159ebe\u010d": [
    14.16446,
    50.13595
  ],
  "Ivanovice na Han\u00e9": [
    17.09343,
    49.30542
  ],
  "Ivan\u010dice": [
    16.37752,
    49.10144
  ],
  "Jablonec nad Jizerou": [
    15.42959,
    50.70347
  ],
  "Jablonec nad Nisou": [
    15.17108,
    50.72431
  ],
  "Jablonn\u00e9 nad Orlic\u00ed": [
    16.60059,
    50.02964
  ],
  "Jablonn\u00e9 v Podje\u0161t\u011bd\u00ed": [
    14.76052,
    50.76528
  ],
  "Jablunkov": [
    18.76458,
    49.57672
  ],
  "Jabl\u016fnka": [
    17.95021,
    49.38355
  ],
  "Jakartovice": [
    17.684,
    49.9151
  ],
  "Jalub\u00ed": [
    17.42788,
    49.11626
  ],
  "Janov nad Nisou": [
    15.16913,
    50.77204
  ],
  "Janovice": [
    18.40602,
    49.62141
  ],
  "Janovice nad \u00dahlavou": [
    13.21813,
    49.34515
  ],
  "Jarom\u011b\u0159": [
    15.92136,
    50.3562
  ],
  "Jarom\u011b\u0159ice": [
    16.75185,
    49.62556
  ],
  "Jarom\u011b\u0159ice nad Rokytnou": [
    15.89331,
    49.09408
  ],
  "Jaroslavice": [
    16.23351,
    48.75657
  ],
  "Jaro\u0161ov nad Ne\u017e\u00e1rkou": [
    15.06734,
    49.18989
  ],
  "Javorn\u00edk": [
    17.00272,
    50.39077
  ],
  "Jedlov\u00e1": [
    16.30608,
    49.661
  ],
  "Jedovnice": [
    16.75595,
    49.34453
  ],
  "Jemnice": [
    15.56994,
    49.01898
  ],
  "Jene\u010d": [
    14.21482,
    50.0873
  ],
  "Jesenice": [
    14.5135,
    49.96814
  ],
  "Jesen\u00edk": [
    17.20464,
    50.22937
  ],
  "Jesen\u00edk nad Odrou": [
    17.90526,
    49.61194
  ],
  "Jevi\u0161ovice": [
    15.98992,
    48.98736
  ],
  "Jev\u00ed\u010dko": [
    16.71125,
    49.6322
  ],
  "Jihlava": [
    15.59124,
    49.3961
  ],
  "Jilemnice": [
    15.50653,
    50.6089
  ],
  "Jimramov": [
    16.22632,
    49.63719
  ],
  "Jince": [
    13.97867,
    49.78624
  ],
  "Jind\u0159ichov": [
    17.51903,
    50.25184
  ],
  "Jind\u0159ich\u016fv Hradec": [
    15.00301,
    49.14404
  ],
  "Jirkov": [
    13.44769,
    50.49979
  ],
  "Jirny": [
    14.69923,
    50.11578
  ],
  "Jistebnice": [
    14.5276,
    49.48553
  ],
  "Jistebn\u00edk": [
    18.13063,
    49.754
  ],
  "Ji\u010d\u00edn": [
    15.35162,
    50.43723
  ],
  "Ji\u0159\u00edkov": [
    14.5691,
    50.99514
  ],
  "Josef\u016fv D\u016fl": [
    15.23146,
    50.78191
  ],
  "J\u00e1chymov": [
    12.93465,
    50.35846
  ],
  "J\u00edlov\u00e9": [
    14.10383,
    50.76082
  ],
  "J\u00edlov\u00e9 u Prahy": [
    14.49333,
    49.89545
  ],
  "Kada\u0148": [
    13.27131,
    50.37598
  ],
  "Kamenice": [
    15.78023,
    49.36659
  ],
  "Kamenice nad Lipou": [
    15.07519,
    49.30303
  ],
  "Kamenick\u00fd \u0160enov": [
    14.47287,
    50.77359
  ],
  "Kamenn\u00e9 \u017dehrovice": [
    14.01809,
    50.12697
  ],
  "Kamenn\u00fd P\u0159\u00edvoz": [
    14.50339,
    49.86299
  ],
  "Kamenn\u00fd \u00dajezd": [
    14.44638,
    48.89753
  ],
  "Kaplice": [
    14.49449,
    48.73881
  ],
  "Karda\u0161ova \u0158e\u010dice": [
    14.85315,
    49.18478
  ],
  "Karlovice": [
    17.44563,
    50.10564
  ],
  "Karlovy Vary": [
    12.87117,
    50.23271
  ],
  "Karl\u00edn": [
    14.44711,
    50.09272
  ],
  "Karolinka": [
    18.24006,
    49.35128
  ],
  "Karvin\u00e1": [
    18.54169,
    49.854
  ],
  "Kasejovice": [
    13.7406,
    49.4627
  ],
  "Katovice": [
    13.83035,
    49.27348
  ],
  "Kazn\u011bjov": [
    13.38295,
    49.89313
  ],
  "Ka\u010dice": [
    13.98815,
    50.16261
  ],
  "Ka\u0161persk\u00e9 Hory": [
    13.55616,
    49.14289
  ],
  "Kbely": [
    14.55,
    50.13333
  ],
  "Kdyn\u011b": [
    13.03968,
    49.39077
  ],
  "Kel\u010d": [
    17.81533,
    49.47844
  ],
  "Kladno": [
    14.10285,
    50.14734
  ],
  "Kladruby": [
    12.98232,
    49.71498
  ],
  "Klatovy": [
    13.29505,
    49.39552
  ],
  "Klecany": [
    14.41148,
    50.17599
  ],
  "Klen\u010d\u00ed pod \u010cerchovem": [
    12.81473,
    49.43484
  ],
  "Klimkovice": [
    18.12585,
    49.78809
  ],
  "Klobouky": [
    16.86298,
    48.99609
  ],
  "Klobuky": [
    13.98748,
    50.29401
  ],
  "Kl\u00e1\u0161ter": [
    12.87623,
    49.96762
  ],
  "Kl\u00e1\u0161terec nad Oh\u0159\u00ed": [
    13.17128,
    50.38445
  ],
  "Kn\u011b\u017edub": [
    17.39546,
    48.88666
  ],
  "Kn\u011b\u017eice": [
    15.67216,
    49.27078
  ],
  "Kn\u011b\u017emost": [
    15.03829,
    50.48917
  ],
  "Kn\u011b\u017epole": [
    17.51671,
    49.09855
  ],
  "Kobe\u0159ice": [
    18.05212,
    49.98548
  ],
  "Kobyl\u00ed": [
    16.89159,
    48.93286
  ],
  "Kojet\u00edn": [
    17.30207,
    49.35179
  ],
  "Kokory": [
    17.37544,
    49.49482
  ],
  "Kolinec": [
    13.439,
    49.29895
  ],
  "Kol\u00edn": [
    15.20057,
    50.02814
  ],
  "Komorn\u00ed Lhotka": [
    18.52777,
    49.65811
  ],
  "Kom\u00e1rov": [
    13.85636,
    49.8065
  ],
  "Konice": [
    16.88911,
    49.5903
  ],
  "Kopidlno": [
    15.27029,
    50.33085
  ],
  "Kop\u0159ivnice": [
    18.1448,
    49.59947
  ],
  "Kory\u010dany": [
    17.16433,
    49.10639
  ],
  "Kosmonosy": [
    14.93,
    50.4385
  ],
  "Kosova Hora": [
    14.47173,
    49.65414
  ],
  "Kostelec na Han\u00e9": [
    17.05824,
    49.51398
  ],
  "Kostelec nad Labem": [
    14.58552,
    50.22653
  ],
  "Kostelec nad Orlic\u00ed": [
    16.21319,
    50.12267
  ],
  "Kostelec nad \u010cern\u00fdmi Lesy": [
    14.85922,
    49.99403
  ],
  "Kostice": [
    16.97869,
    48.74685
  ],
  "Kout na \u0160umav\u011b": [
    13.00208,
    49.40255
  ],
  "Kou\u0159im": [
    14.97703,
    50.00306
  ],
  "Kov\u00e1\u0159ov": [
    14.27809,
    49.5176
  ],
  "Kov\u00e1\u0159sk\u00e1": [
    13.05388,
    50.43821
  ],
  "Kozlovice": [
    18.25656,
    49.5904
  ],
  "Kozmice": [
    18.15584,
    49.9128
  ],
  "Ko\u0159enov": [
    15.36532,
    50.75926
  ],
  "Ko\u0161\u0165any": [
    13.75554,
    50.65507
  ],
  "Ko\u0161\u0165\u00e1lov": [
    15.40403,
    50.57165
  ],
  "Ko\u017elany": [
    13.54107,
    49.99389
  ],
  "Kralice na Han\u00e9": [
    17.18048,
    49.46296
  ],
  "Kralovice": [
    13.48747,
    49.98192
  ],
  "Kralupy nad Vltavou": [
    14.31149,
    50.24107
  ],
  "Kraslice": [
    12.51747,
    50.32372
  ],
  "Krava\u0159e": [
    18.00472,
    49.93203
  ],
  "Krmel\u00edn": [
    18.23541,
    49.72914
  ],
  "Krnov": [
    17.70385,
    50.08967
  ],
  "Krom\u011b\u0159\u00ed\u017e": [
    17.39312,
    49.29785
  ],
  "Krouna": [
    16.02674,
    49.7724
  ],
  "Krumv\u00ed\u0159": [
    16.91027,
    48.98901
  ],
  "Krupka": [
    13.85815,
    50.68449
  ],
  "Kryry": [
    13.4266,
    50.17437
  ],
  "Kr\u00e1l\u00edky": [
    16.76054,
    50.08384
  ],
  "Kr\u00e1l\u016fv Dv\u016fr": [
    14.03445,
    49.94981
  ],
  "Kr\u00e1sn\u00e1 Hora nad Vltavou": [
    14.27742,
    49.60461
  ],
  "Kr\u00e1sn\u00e1 L\u00edpa": [
    13.3575,
    50.48378
  ],
  "Kunovice": [
    17.47011,
    49.04499
  ],
  "Kunvald": [
    16.49996,
    50.12927
  ],
  "Kun\u00edn": [
    17.98965,
    49.63377
  ],
  "Kun\u010dice pod Ond\u0159ejn\u00edkem": [
    18.26113,
    49.5507
  ],
  "Kun\u010dina": [
    16.62763,
    49.79455
  ],
  "Kun\u0161t\u00e1t": [
    16.51722,
    49.50645
  ],
  "Kun\u017eak": [
    15.19028,
    49.12119
  ],
  "Kutn\u00e1 Hora": [
    15.26816,
    49.94839
  ],
  "Ku\u0159im": [
    16.53144,
    49.29852
  ],
  "Kvasice": [
    17.46974,
    49.24223
  ],
  "Kvasiny": [
    16.26323,
    50.2125
  ],
  "Kyjov": [
    17.12253,
    49.01018
  ],
  "Kyn\u0161perk nad Oh\u0159\u00ed": [
    12.53027,
    50.11893
  ],
  "K\u00e1jov": [
    14.25859,
    48.81082
  ],
  "K\u0159em\u017ee": [
    14.30568,
    48.90497
  ],
  "K\u0159enovice": [
    16.82932,
    49.14216
  ],
  "K\u0159epice": [
    16.71989,
    48.99986
  ],
  "K\u0159e\u0161ice": [
    14.2145,
    50.52259
  ],
  "K\u0159inec": [
    15.13782,
    50.26449
  ],
  "K\u0159i\u017eanov": [
    16.1096,
    49.38858
  ],
  "K\u0159\u00ed\u017eov\u00e1": [
    15.85207,
    49.68841
  ],
  "Lan\u0161kroun": [
    16.6119,
    49.91217
  ],
  "Lan\u017ehot": [
    16.96695,
    48.72443
  ],
  "Ledenice": [
    14.61886,
    48.93329
  ],
  "Lede\u010d nad S\u00e1zavou": [
    15.27772,
    49.69517
  ],
  "Lednice": [
    16.80339,
    48.79992
  ],
  "Lelekovice": [
    16.57874,
    49.29144
  ],
  "Lene\u0161ice": [
    13.7659,
    50.37516
  ],
  "Letohrad": [
    16.49879,
    50.0358
  ],
  "Letonice": [
    16.95913,
    49.17726
  ],
  "Letovice": [
    16.57357,
    49.54709
  ],
  "Let\u0148any": [
    14.51667,
    50.13333
  ],
  "Le\u0161n\u00e1": [
    17.93004,
    49.52055
  ],
  "Le\u0161tina": [
    16.92748,
    49.86879
  ],
  "Lhenice": [
    14.1498,
    48.99479
  ],
  "Liberec": [
    15.05619,
    50.76711
  ],
  "Libe\u0148": [
    14.47457,
    50.10819
  ],
  "Libice nad Cidlinou": [
    15.1782,
    50.12677
  ],
  "Libi\u0161": [
    14.5024,
    50.27417
  ],
  "Libochovice": [
    14.04439,
    50.40626
  ],
  "Libouchec": [
    14.04071,
    50.75854
  ],
  "Libu\u0161\u00edn": [
    14.05458,
    50.16819
  ],
  "Lib\u00e1\u0148": [
    15.21684,
    50.37542
  ],
  "Lib\u010dice nad Vltavou": [
    14.36385,
    50.19778
  ],
  "Lib\u011b\u0161ice": [
    14.28906,
    50.56886
  ],
  "Lichnov": [
    17.6264,
    50.00786
  ],
  "Lichnov (o. Nov\u00fd Ji\u010d\u00edn)": [
    18.16898,
    49.56423
  ],
  "Lide\u010dko": [
    18.0513,
    49.20303
  ],
  "Lipn\u00edk nad Be\u010dvou": [
    17.58594,
    49.52721
  ],
  "Lipov": [
    17.46171,
    48.90495
  ],
  "Lipovec": [
    16.80583,
    49.38394
  ],
  "Lipt\u00e1l": [
    17.92177,
    49.29051
  ],
  "Lip\u016fvka": [
    16.55313,
    49.33933
  ],
  "Litomy\u0161l": [
    16.31298,
    49.86809
  ],
  "Litom\u011b\u0159ice": [
    14.1318,
    50.53348
  ],
  "Litovel": [
    17.07615,
    49.70121
  ],
  "Litv\u00ednov": [
    13.61812,
    50.6042
  ],
  "Litv\u00ednovice": [
    14.45146,
    48.96207
  ],
  "Li\u0161ov": [
    14.60838,
    49.01597
  ],
  "Lochovice": [
    13.98126,
    49.85318
  ],
  "Lod\u011bnice": [
    14.15785,
    49.99486
  ],
  "Loket": [
    12.75405,
    50.186
  ],
  "Lom u Mostu": [
    13.65729,
    50.59328
  ],
  "Lomnice": [
    16.41359,
    49.40462
  ],
  "Lomnice nad Lu\u017enic\u00ed": [
    14.71727,
    49.08468
  ],
  "Lomnice nad Popelkou": [
    15.37341,
    50.53062
  ],
  "Louka": [
    17.48927,
    48.91517
  ],
  "Louny": [
    13.79667,
    50.35699
  ],
  "Lou\u010de\u0148": [
    15.02049,
    50.28537
  ],
  "Lou\u010dn\u00e1 nad Desnou": [
    17.09052,
    50.07433
  ],
  "Lou\u010dovice": [
    14.24976,
    48.6209
  ],
  "Lovosice": [
    14.05103,
    50.51504
  ],
  "Lo\u0161tice": [
    16.92892,
    49.7447
  ],
  "Lubenec": [
    13.31319,
    50.13207
  ],
  "Luby": [
    12.40595,
    50.25248
  ],
  "Ludge\u0159ovice": [
    18.24008,
    49.89042
  ],
  "Luha\u010dovice": [
    17.75747,
    49.09982
  ],
  "Luka nad Jihlavou": [
    15.70194,
    49.37403
  ],
  "Lukavec": [
    14.99041,
    49.56541
  ],
  "Lukavice": [
    16.48207,
    50.06029
  ],
  "Lukov": [
    17.72959,
    49.29027
  ],
  "Lut\u00edn": [
    17.13572,
    49.55845
  ],
  "Lu\u010dany nad Nisou": [
    15.22046,
    50.74136
  ],
  "Lu\u010dina": [
    18.44776,
    49.72082
  ],
  "Lu\u0161t\u011bnice": [
    14.93667,
    50.32296
  ],
  "Lu\u017ee": [
    16.0285,
    49.89341
  ],
  "Lu\u017eec nad Vltavou": [
    14.40022,
    50.32138
  ],
  "Lu\u017eice": [
    17.07104,
    48.84098
  ],
  "Lu\u017en\u00e1": [
    13.77004,
    50.12377
  ],
  "Lysice": [
    16.53716,
    49.4516
  ],
  "Lys\u00e1 nad Labem": [
    14.83281,
    50.20143
  ],
  "L\u00e1ny": [
    13.95041,
    50.12471
  ],
  "L\u00e1zn\u011b Bohdane\u010d": [
    15.67978,
    50.0756
  ],
  "L\u00e1zn\u011b B\u011blohrad": [
    15.58269,
    50.42874
  ],
  "L\u00e1zn\u011b Kyn\u017evart": [
    12.62474,
    50.01058
  ],
  "L\u00edbeznice": [
    14.49357,
    50.19198
  ],
  "L\u00edn\u011b": [
    13.25693,
    49.69472
  ],
  "L\u00edpa": [
    15.54465,
    49.55418
  ],
  "Machov": [
    16.2769,
    50.49927
  ],
  "Majet\u00edn": [
    17.33314,
    49.49808
  ],
  "Malonty": [
    14.57678,
    48.68611
  ],
  "Mal\u00e1 Sk\u00e1la": [
    15.19543,
    50.64631
  ],
  "Mal\u00e1 Strana": [
    14.40449,
    50.08774
  ],
  "Mal\u00e9 Svato\u0148ovice": [
    16.04978,
    50.53395
  ],
  "Mal\u0161ice": [
    14.57868,
    49.36391
  ],
  "Man\u011bt\u00edn": [
    13.23319,
    49.99177
  ],
  "Mari\u00e1nsk\u00e9 L\u00e1zn\u011b": [
    12.70118,
    49.96459
  ],
  "Markvartovice": [
    18.23602,
    49.90595
  ],
  "Meclov": [
    12.88082,
    49.50556
  ],
  "Medlov": [
    17.06261,
    49.78754
  ],
  "Merkl\u00edn": [
    13.1979,
    49.56043
  ],
  "Metylovice": [
    18.33911,
    49.60666
  ],
  "Mezibo\u0159i": [
    13.5987,
    50.62115
  ],
  "Mezim\u011bst\u00ed": [
    16.24207,
    50.62461
  ],
  "Mikulov": [
    16.6378,
    48.80556
  ],
  "Mikulovice": [
    17.32155,
    50.29854
  ],
  "Mikul\u00e1\u0161ovice": [
    14.36368,
    50.96507
  ],
  "Mikul\u010dice": [
    17.05107,
    48.81643
  ],
  "Milevsko": [
    14.36,
    49.45089
  ],
  "Milotice": [
    17.14241,
    48.95528
  ],
  "Milovice": [
    14.88863,
    50.22596
  ],
  "Mil\u00edkov": [
    18.71943,
    49.58565
  ],
  "Mil\u00edn": [
    14.046,
    49.63192
  ],
  "Mimo\u0148": [
    14.72474,
    50.65869
  ],
  "Miroslav": [
    16.31252,
    48.94767
  ],
  "Mirotice": [
    14.03697,
    49.42908
  ],
  "Mirovice": [
    14.03582,
    49.51555
  ],
  "Miro\u0161ov": [
    13.65807,
    49.68782
  ],
  "Mist\u0159ice": [
    17.53597,
    49.08668
  ],
  "Mi\u0159etice": [
    15.88472,
    49.84126
  ],
  "Mlad\u00e1 Boleslav": [
    14.90318,
    50.41135
  ],
  "Mlad\u00e1 Vo\u017eice": [
    14.80857,
    49.53313
  ],
  "Mlad\u00e9 Buky": [
    15.83348,
    50.60643
  ],
  "Mnichovice": [
    14.70907,
    49.93601
  ],
  "Mnichovo Hradi\u0161t\u011b": [
    14.97134,
    50.5272
  ],
  "Mn\u00ed\u0161ek": [
    15.0563,
    50.83163
  ],
  "Mn\u00ed\u0161ek pod Brdy": [
    14.26176,
    49.8665
  ],
  "Mod\u0159any": [
    14.4096,
    50.01116
  ],
  "Mod\u0159ice": [
    16.60446,
    49.11928
  ],
  "Mohelnice": [
    16.91946,
    49.77698
  ],
  "Mohelno": [
    16.19022,
    49.11412
  ],
  "Mokr\u00e1 Hora": [
    16.59107,
    49.26176
  ],
  "Mokr\u00e9 Lazce": [
    18.02954,
    49.90462
  ],
  "Moravany": [
    16.58026,
    49.1478
  ],
  "Moravi\u010dany": [
    16.96042,
    49.75694
  ],
  "Moravsk\u00e1 Nov\u00e1 Ves": [
    17.01371,
    48.80304
  ],
  "Moravsk\u00e1 T\u0159ebov\u00e1": [
    16.66426,
    49.75793
  ],
  "Moravsk\u00e9 Bud\u011bjovice": [
    15.80864,
    49.05209
  ],
  "Moravsk\u00fd Beroun": [
    17.44212,
    49.79374
  ],
  "Moravsk\u00fd Krumlov": [
    16.31169,
    49.04893
  ],
  "Moravsk\u00fd P\u00edsek": [
    17.33269,
    48.99016
  ],
  "Moravsk\u00fd \u017di\u017ekov": [
    16.9314,
    48.83285
  ],
  "Mor\u00e1vka": [
    18.52471,
    49.59607
  ],
  "Most": [
    13.63617,
    50.50301
  ],
  "Mostek": [
    15.69622,
    50.48623
  ],
  "Mostkovice": [
    17.05212,
    49.47215
  ],
  "Mosty u Jablunkova": [
    18.75417,
    49.52737
  ],
  "Moutnice": [
    16.73741,
    49.04924
  ],
  "Mo\u0159kov": [
    18.05968,
    49.53684
  ],
  "Mr\u00e1kov": [
    12.9512,
    49.40314
  ],
  "Muka\u0159ov": [
    14.74155,
    49.99115
  ],
  "Mut\u011bnice": [
    17.02917,
    48.90413
  ],
  "M\u00fdto": [
    13.73461,
    49.78904
  ],
  "M\u011bcholupy": [
    13.53737,
    50.26666
  ],
  "M\u011bln\u00edk": [
    14.47411,
    50.3505
  ],
  "M\u011bn\u00edn": [
    16.69424,
    49.0824
  ],
  "M\u011bstec Kr\u00e1lov\u00e9": [
    15.29758,
    50.20718
  ],
  "M\u011bste\u010dko Trn\u00e1vka": [
    16.72744,
    49.70926
  ],
  "M\u011bsto": [
    12.86432,
    49.97997
  ],
  "M\u011bsto Albrechtice": [
    17.57481,
    50.16294
  ],
  "M\u011bsto Libav\u00e1": [
    17.52013,
    49.72162
  ],
  "M\u011bsto Tou\u0161kov": [
    13.25108,
    49.77587
  ],
  "M\u011b\u010d\u00edn": [
    13.40289,
    49.48009
  ],
  "M\u011b\u0159\u00edn": [
    15.88381,
    49.39321
  ],
  "M\u011b\u0161ice": [
    14.51992,
    50.19799
  ],
  "M\u0161eno": [
    14.6325,
    50.43809
  ],
  "Napajedla": [
    17.51194,
    49.17156
  ],
  "Nasavrky": [
    15.80461,
    49.8445
  ],
  "Na\u010deradec": [
    14.90633,
    49.61018
  ],
  "Nechanice": [
    15.63276,
    50.23737
  ],
  "Nedakonice": [
    17.38141,
    49.03159
  ],
  "Neda\u0161ov": [
    18.07036,
    49.10778
  ],
  "Nedv\u011bdice": [
    16.33406,
    49.45702
  ],
  "Nehvizdy": [
    14.72993,
    50.13056
  ],
  "Nejdek": [
    12.72936,
    50.32242
  ],
  "Nelahozeves": [
    14.29881,
    50.26148
  ],
  "Nepomuk": [
    13.58225,
    49.48616
  ],
  "Neratovice": [
    14.51759,
    50.25926
  ],
  "Nesovice": [
    17.08095,
    49.15111
  ],
  "Netolice": [
    14.197,
    49.0493
  ],
  "Netvo\u0159ice": [
    14.51827,
    49.81569
  ],
  "Neveklov": [
    14.53291,
    49.75373
  ],
  "Nezamyslice": [
    17.17326,
    49.32543
  ],
  "Nezv\u011bstice": [
    13.51962,
    49.64043
  ],
  "Nivnice": [
    17.64757,
    48.97465
  ],
  "Ni\u017ebor": [
    14.00237,
    49.99995
  ],
  "Nosislav": [
    16.65431,
    49.0138
  ],
  "Novosedlice": [
    13.82304,
    50.65633
  ],
  "Novosedly": [
    16.49273,
    48.83704
  ],
  "Nov\u00e1 Byst\u0159ice": [
    15.10316,
    49.01926
  ],
  "Nov\u00e1 Cerekev": [
    15.11675,
    49.41723
  ],
  "Nov\u00e1 Paka": [
    15.51503,
    50.49449
  ],
  "Nov\u00e1 Role": [
    12.78422,
    50.27092
  ],
  "Nov\u00e1 V\u010delnice": [
    15.0726,
    49.23935
  ],
  "Nov\u00e9 Hrady": [
    14.77839,
    48.78963
  ],
  "Nov\u00e9 M\u011bsto na Morav\u011b": [
    16.07418,
    49.56144
  ],
  "Nov\u00e9 M\u011bsto nad Metuj\u00ed": [
    16.15147,
    50.34456
  ],
  "Nov\u00e9 M\u011bsto pod Smrkem": [
    15.22943,
    50.92491
  ],
  "Nov\u00e9 Sedlo": [
    12.738,
    50.20647
  ],
  "Nov\u00e9 Stra\u0161ec\u00ed": [
    13.90043,
    50.15272
  ],
  "Nov\u00e9 Syrovice": [
    15.77345,
    49.01763
  ],
  "Nov\u00e9 Vesel\u00ed": [
    15.90853,
    49.51976
  ],
  "Nov\u00fd Bor": [
    14.55555,
    50.75761
  ],
  "Nov\u00fd Byd\u017eov": [
    15.49082,
    50.2415
  ],
  "Nov\u00fd Hrozenkov": [
    18.19793,
    49.33697
  ],
  "Nov\u00fd Ji\u010d\u00edn": [
    18.01028,
    49.59438
  ],
  "Nov\u00fd Kn\u00edn": [
    14.29355,
    49.788
  ],
  "Nov\u00fd Mal\u00edn": [
    17.03191,
    49.94262
  ],
  "Nymburk": [
    15.04167,
    50.18605
  ],
  "N\u00e1chod": [
    16.16289,
    50.4167
  ],
  "N\u00e1klo": [
    17.12969,
    49.65462
  ],
  "N\u00e1m\u011b\u0161\u0165 na Han\u00e9": [
    17.06539,
    49.60213
  ],
  "N\u00e1m\u011b\u0161\u0165 nad Oslavou": [
    16.15849,
    49.20726
  ],
  "N\u00e1vs\u00ed u Jablunkova": [
    18.75907,
    49.5872
  ],
  "N\u00fddek": [
    18.75687,
    49.65609
  ],
  "N\u00fdrsko": [
    13.14353,
    49.29387
  ],
  "N\u00fd\u0159any": [
    13.21185,
    49.71145
  ],
  "N\u011bm\u010dice nad Hanou": [
    17.20596,
    49.34181
  ],
  "Obecnice": [
    13.94731,
    49.71615
  ],
  "Obrnice": [
    13.6954,
    50.50498
  ],
  "Odolena Voda": [
    14.41078,
    50.23341
  ],
  "Odry": [
    17.83084,
    49.66255
  ],
  "Ohrazenice": [
    15.12596,
    50.59765
  ],
  "Okrouhlice": [
    15.49083,
    49.62991
  ],
  "Ok\u0159\u00ed\u0161ky": [
    15.76959,
    49.24539
  ],
  "Olbramovice": [
    16.40239,
    48.9848
  ],
  "Old\u0159i\u0161ov": [
    17.96074,
    49.9913
  ],
  "Ole\u0161nice": [
    16.42169,
    49.55755
  ],
  "Olomouc": [
    17.25175,
    49.59552
  ],
  "Olov\u00ed": [
    12.55877,
    50.25113
  ],
  "Ol\u0161any": [
    16.85894,
    49.96509
  ],
  "Ond\u0159ejov": [
    14.7842,
    49.90461
  ],
  "Opatov": [
    16.50458,
    49.825
  ],
  "Opatovice nad Labem": [
    15.79045,
    50.14541
  ],
  "Opava": [
    17.90257,
    49.93866
  ],
  "Opa\u0159any": [
    14.48137,
    49.39678
  ],
  "Opo\u010dno": [
    16.1148,
    50.26742
  ],
  "Orlov\u00e1": [
    18.43011,
    49.84527
  ],
  "Osek": [
    13.5906,
    49.77594
  ],
  "Osek nad Be\u010dvou": [
    17.52829,
    49.51121
  ],
  "Ose\u010dn\u00e1": [
    14.92138,
    50.69489
  ],
  "Oskava": [
    17.13214,
    49.89523
  ],
  "Oslavany": [
    16.33653,
    49.12335
  ],
  "Osoblaha": [
    17.71523,
    50.27517
  ],
  "Ostopovice": [
    16.54548,
    49.161
  ],
  "Ostrava": [
    18.28204,
    49.83465
  ],
  "Ostravice": [
    18.39164,
    49.5351
  ],
  "Ostrom\u011b\u0159": [
    15.54949,
    50.37246
  ],
  "Ostrov": [
    12.93907,
    50.30592
  ],
  "Ostrov u Macochy": [
    16.76268,
    49.38236
  ],
  "Ostro\u017esk\u00e1 Lhota": [
    17.46751,
    48.97559
  ],
  "Ostro\u017esk\u00e1 Nov\u00e1 Ves": [
    17.43632,
    49.00434
  ],
  "Os\u00edk": [
    16.28467,
    49.84355
  ],
  "Otaslavice": [
    17.07108,
    49.38833
  ],
  "Otice": [
    17.86982,
    49.91684
  ],
  "Otnice": [
    16.81443,
    49.08642
  ],
  "Otrokovice": [
    17.53944,
    49.20934
  ],
  "O\u0159echov": [
    16.52329,
    49.11118
  ],
  "Pacov": [
    15.00168,
    49.47076
  ],
  "Palkovice": [
    18.31508,
    49.63467
  ],
  "Pardubice": [
    15.77659,
    50.04075
  ],
  "Paseka": [
    17.22276,
    49.79644
  ],
  "Paskov": [
    18.29037,
    49.73179
  ],
  "Pavl\u00edkov": [
    13.73636,
    50.05599
  ],
  "Pchery": [
    14.11782,
    50.19378
  ],
  "Pecka": [
    15.60822,
    50.48034
  ],
  "Pelh\u0159imov": [
    15.22336,
    49.43134
  ],
  "Peruc": [
    13.95986,
    50.3425
  ],
  "Per\u0161tejn": [
    13.1102,
    50.38166
  ],
  "Petrov": [
    17.2781,
    48.88196
  ],
  "Petrovice": [
    14.33737,
    49.55426
  ],
  "Petrovice u Karvin\u00e9": [
    18.54779,
    49.89587
  ],
  "Pet\u0159vald": [
    18.15719,
    49.70872
  ],
  "Pe\u010dky": [
    15.03017,
    50.09043
  ],
  "Piln\u00edkov": [
    15.8202,
    50.53247
  ],
  "Plan\u00e1": [
    12.74378,
    49.86816
  ],
  "Plan\u00e1 nad Lu\u017enic\u00ed": [
    14.70147,
    49.35444
  ],
  "Plasy": [
    13.39035,
    49.93449
  ],
  "Plavy": [
    15.31736,
    50.70324
  ],
  "Pla\u0148any": [
    15.02944,
    50.0501
  ],
  "Plesn\u00e1": [
    12.34669,
    50.2207
  ],
  "Plumlov": [
    17.01502,
    49.46614
  ],
  "Plze\u0148": [
    13.37759,
    49.74747
  ],
  "Pl\u00e1nice": [
    13.47106,
    49.38993
  ],
  "Pob\u011b\u017eovice": [
    12.80261,
    49.51029
  ],
  "Podbo\u0159any": [
    13.41192,
    50.22937
  ],
  "Podiv\u00edn": [
    16.84822,
    48.82554
  ],
  "Podol\u00ed": [
    16.72084,
    49.19042
  ],
  "Pod\u011bbrady": [
    15.11881,
    50.14242
  ],
  "Poho\u0159elice": [
    16.52445,
    48.98119
  ],
  "Polepy": [
    14.26447,
    50.50563
  ],
  "Pole\u0161ovice": [
    17.34064,
    49.0339
  ],
  "Police nad Metuj\u00ed": [
    16.2335,
    50.53687
  ],
  "Poli\u010dka": [
    16.26543,
    49.71465
  ],
  "Poln\u00e1": [
    15.71881,
    49.487
  ],
  "Pomez\u00ed": [
    16.31729,
    49.71026
  ],
  "Ponikl\u00e1": [
    15.46329,
    50.66152
  ],
  "Popovice": [
    17.52712,
    49.05255
  ],
  "Postoloprty": [
    13.70291,
    50.35979
  ],
  "Postupice": [
    14.77722,
    49.72798
  ],
  "Post\u0159ekov": [
    12.80678,
    49.45827
  ],
  "Post\u0159elmov": [
    16.91226,
    49.90756
  ],
  "Pot\u0161t\u00e1t": [
    17.65174,
    49.63693
  ],
  "Povrly": [
    14.16033,
    50.67276
  ],
  "Pozlovice": [
    17.76925,
    49.12921
  ],
  "Pozo\u0159ice": [
    16.79074,
    49.20976
  ],
  "Po\u010d\u00e1tky": [
    15.24022,
    49.2602
  ],
  "Po\u0159\u00ed\u010dany": [
    14.91818,
    50.10806
  ],
  "Po\u0159\u00ed\u010d\u00ed nad S\u00e1zavou": [
    14.67446,
    49.83895
  ],
  "Prachatice": [
    13.99752,
    49.01292
  ],
  "Prachovice": [
    15.62872,
    49.89379
  ],
  "Prague": [
    14.42076,
    50.08804
  ],
  "Pra\u017emo": [
    18.48617,
    49.60876
  ],
  "Probo\u0161tov": [
    13.83601,
    50.66773
  ],
  "Prosek": [
    14.50685,
    50.11525
  ],
  "Prose\u010d": [
    16.11621,
    49.8059
  ],
  "Prost\u011bjov": [
    17.11184,
    49.47188
  ],
  "Prost\u0159edn\u00ed Be\u010dva": [
    18.252,
    49.43609
  ],
  "Protivanov": [
    16.83594,
    49.48351
  ],
  "Protiv\u00edn": [
    14.21717,
    49.19949
  ],
  "Prusinovice": [
    17.5871,
    49.37898
  ],
  "Pru\u0161\u00e1nky": [
    16.98068,
    48.8284
  ],
  "Pr\u016fhonice": [
    14.55017,
    49.99962
  ],
  "Ps\u00e1ry": [
    14.51276,
    49.93622
  ],
  "Pten\u00ed": [
    16.9611,
    49.51163
  ],
  "Pustim\u011b\u0159": [
    17.02792,
    49.32251
  ],
  "Pust\u00e1 Polom": [
    17.9979,
    49.84917
  ],
  "Py\u0161ely": [
    14.67713,
    49.87678
  ],
  "P\u00edsek": [
    14.1475,
    49.3088
  ],
  "P\u00edse\u010dn\u00e1": [
    17.25373,
    50.27303
  ],
  "P\u00ed\u0161\u0165": [
    18.19349,
    49.97857
  ],
  "P\u011bn\u010d\u00edn": [
    15.23593,
    50.68769
  ],
  "P\u0159edkl\u00e1\u0161te\u0159\u00ed": [
    16.40241,
    49.35253
  ],
  "P\u0159edm\u011b\u0159ice nad Labem": [
    15.81556,
    50.25633
  ],
  "P\u0159elou\u010d": [
    15.56031,
    50.03985
  ],
  "P\u0159emyslovice": [
    16.95581,
    49.55637
  ],
  "P\u0159erov": [
    17.4509,
    49.45511
  ],
  "P\u0159erov nad Labem": [
    14.82502,
    50.16027
  ],
  "P\u0159e\u0161tice": [
    13.3335,
    49.57298
  ],
  "P\u0159ibyslav": [
    15.73855,
    49.57684
  ],
  "P\u0159imda": [
    12.67366,
    49.67488
  ],
  "P\u0159\u00e1slavice": [
    17.38209,
    49.58568
  ],
  "P\u0159\u00edbor": [
    18.14499,
    49.64094
  ],
  "P\u0159\u00edbram": [
    14.01043,
    49.68988
  ],
  "P\u0159\u00edkazy": [
    17.14337,
    49.6436
  ],
  "P\u0159\u00ed\u0161ovice": [
    15.0839,
    50.57813
  ],
  "Radim\u011b\u0159": [
    16.4407,
    49.6985
  ],
  "Radnice": [
    13.6057,
    49.85677
  ],
  "Radomy\u0161l": [
    13.93024,
    49.31634
  ],
  "Radonice": [
    13.28464,
    50.29803
  ],
  "Radslavice": [
    17.51656,
    49.47817
  ],
  "Radvanice": [
    16.06172,
    50.56745
  ],
  "Rajhrad": [
    16.60388,
    49.09021
  ],
  "Rajhradice": [
    16.62933,
    49.09203
  ],
  "Rakovn\u00edk": [
    13.7334,
    50.1037
  ],
  "Rakvice": [
    16.8133,
    48.85811
  ],
  "Rapot\u00edn": [
    17.03121,
    50.01094
  ],
  "Raspenava": [
    15.11465,
    50.90415
  ],
  "Rataje": [
    17.33555,
    49.2713
  ],
  "Ratibo\u0159": [
    17.91499,
    49.36769
  ],
  "Rat\u00ed\u0161kovice": [
    17.16561,
    48.92002
  ],
  "Ra\u0161kovice": [
    18.47286,
    49.61975
  ],
  "Rohatec": [
    17.1833,
    48.8804
  ],
  "Rokycany": [
    13.59459,
    49.7427
  ],
  "Rokytnice": [
    17.3912,
    49.46592
  ],
  "Rokytnice nad Jizerou": [
    15.43357,
    50.72561
  ],
  "Rokytnice v Orlick\u00fdch Hor\u00e1ch": [
    16.46567,
    50.16473
  ],
  "Ronov nad Doubravou": [
    15.53144,
    49.88825
  ],
  "Ropice": [
    18.61345,
    49.70536
  ],
  "Rosice": [
    16.38787,
    49.18232
  ],
  "Rotava": [
    12.57341,
    50.29627
  ],
  "Rouchovany": [
    16.1076,
    49.07036
  ],
  "Roudnice nad Labem": [
    14.26175,
    50.42528
  ],
  "Rous\u00ednov": [
    16.88215,
    49.20128
  ],
  "Rovensko pod Troskami": [
    15.25941,
    50.53532
  ],
  "Roztoky": [
    13.86787,
    50.02671
  ],
  "Ro\u017emit\u00e1l pod T\u0159em\u0161\u00ednem": [
    13.8643,
    49.60196
  ],
  "Ro\u017enov pod Radho\u0161t\u011bm": [
    18.14302,
    49.45853
  ],
  "Ro\u017e\u010falovice": [
    15.16962,
    50.30476
  ],
  "Rtyn\u011b v Podkrkono\u0161\u00ed": [
    16.07187,
    50.50523
  ],
  "Ruda nad Moravou": [
    16.87782,
    49.981
  ],
  "Rudn\u00e1": [
    14.23435,
    50.03502
  ],
  "Rudn\u00edk": [
    15.73362,
    50.59517
  ],
  "Rudolfov": [
    14.54179,
    48.99339
  ],
  "Rumburk": [
    14.55699,
    50.95151
  ],
  "Rybitv\u00ed": [
    15.70472,
    50.06015
  ],
  "Ryb\u00ed": [
    18.07592,
    49.60073
  ],
  "Rychnov nad Kn\u011b\u017enou": [
    16.27488,
    50.16284
  ],
  "Rychvald": [
    18.37626,
    49.86625
  ],
  "R\u00e1jec-Jest\u0159eb\u00ed": [
    16.63902,
    49.41094
  ],
  "R\u00e1je\u010dko": [
    16.64497,
    49.39393
  ],
  "R\u00fdma\u0159ov": [
    17.27177,
    49.93183
  ],
  "Sadov": [
    12.89708,
    50.26711
  ],
  "Sadsk\u00e1": [
    14.98633,
    50.13596
  ],
  "Samot\u00ed\u0161ky": [
    17.32807,
    49.63042
  ],
  "Satalice": [
    14.56701,
    50.12405
  ],
  "Sedlice": [
    14.39115,
    48.77401
  ],
  "Sedli\u0161t\u011b": [
    18.36869,
    49.71836
  ],
  "Sedlnice": [
    18.0869,
    49.6577
  ],
  "Sedl\u010dany": [
    14.42664,
    49.66057
  ],
  "Semily": [
    15.33552,
    50.60191
  ],
  "Senice na Han\u00e9": [
    17.08578,
    49.62401
  ],
  "Sepekov": [
    14.41815,
    49.42865
  ],
  "Sezemice": [
    15.8527,
    50.06651
  ],
  "Sezimovo \u00dast\u00ed": [
    14.6848,
    49.38519
  ],
  "Se\u010d": [
    15.65643,
    49.84694
  ],
  "Skaln\u00e1": [
    12.36144,
    50.1703
  ],
  "Skrbe\u0148": [
    17.1765,
    49.64115
  ],
  "Skuhrov nad B\u011blou": [
    16.2923,
    50.22946
  ],
  "Skute\u010d": [
    15.99655,
    49.84347
  ],
  "Slan\u00fd": [
    14.08693,
    50.23046
  ],
  "Slatinice": [
    17.09992,
    49.56155
  ],
  "Slati\u0148any": [
    15.81377,
    49.9211
  ],
  "Slavi\u010d\u00edn": [
    17.87349,
    49.08799
  ],
  "Slavkov": [
    17.83641,
    49.9218
  ],
  "Slavkov u Brna": [
    16.87649,
    49.15325
  ],
  "Slavonice": [
    15.35154,
    48.99753
  ],
  "Slu\u0161ovice": [
    17.8015,
    49.24782
  ],
  "Sme\u010dno": [
    14.04037,
    50.18844
  ],
  "Smidary": [
    15.47725,
    50.29146
  ],
  "Smi\u0159ice": [
    15.86508,
    50.29978
  ],
  "Smr\u017eice": [
    17.10698,
    49.50569
  ],
  "Smr\u017eovka": [
    15.24639,
    50.7382
  ],
  "Sobotka": [
    15.17619,
    50.46741
  ],
  "Sobot\u00edn": [
    17.09129,
    50.01039
  ],
  "Sob\u011bslav": [
    14.71861,
    49.25993
  ],
  "Sokolnice": [
    16.72156,
    49.11392
  ],
  "Sokolov": [
    12.6401,
    50.1813
  ],
  "Solnice": [
    16.23762,
    50.20366
  ],
  "Spytihn\u011bv": [
    17.49808,
    49.14115
  ],
  "Sp\u00e1len\u00e9 Po\u0159\u00ed\u010d\u00ed": [
    13.60556,
    49.61371
  ],
  "Srubec": [
    14.54131,
    48.94806
  ],
  "Stachy": [
    13.66659,
    49.10179
  ],
  "Star\u00e1 Hu\u0165": [
    14.19735,
    49.78225
  ],
  "Star\u00e1 Paka": [
    15.49444,
    50.51032
  ],
  "Star\u00e1 Ves nad Ond\u0159ejnic\u00ed": [
    18.1885,
    49.72775
  ],
  "Star\u00e9 Hradi\u0161t\u011b": [
    15.77885,
    50.0654
  ],
  "Star\u00e9 K\u0159e\u010dany": [
    14.49617,
    50.95044
  ],
  "Star\u00e9 M\u011bsto": [
    17.43338,
    49.07515
  ],
  "Star\u00e9 Nechanice": [
    15.61787,
    50.24298
  ],
  "Star\u00fd Bohum\u00edn": [
    18.33619,
    49.9169
  ],
  "Star\u00fd Ji\u010d\u00edn": [
    17.96169,
    49.57686
  ],
  "Star\u00fd Kol\u00edn": [
    15.29388,
    50.00977
  ],
  "Star\u00fd Plzenec": [
    13.4735,
    49.69768
  ],
  "Sta\u0148kov": [
    13.06976,
    49.55348
  ],
  "Sta\u0159e\u010d": [
    15.82791,
    49.19783
  ],
  "Sta\u0159\u00ed\u010d": [
    18.27281,
    49.68594
  ],
  "Stochov": [
    13.96345,
    50.14631
  ],
  "Stod": [
    13.16474,
    49.63909
  ],
  "Stonava": [
    18.52518,
    49.81691
  ],
  "Strakonice": [
    13.90237,
    49.26141
  ],
  "Stran\u010dice": [
    14.67745,
    49.94811
  ],
  "Stra\u0161ice": [
    13.75755,
    49.73552
  ],
  "Strmilov": [
    15.19934,
    49.15846
  ],
  "Strunkovice nad Blanic\u00ed": [
    14.05522,
    49.08402
  ],
  "Str\u00e1n\u00ed": [
    17.70671,
    48.90216
  ],
  "Str\u00e1\u017e": [
    12.77546,
    49.66878
  ],
  "Str\u00e1\u017e nad Nisou": [
    15.02683,
    50.79099
  ],
  "Str\u00e1\u017e pod Ralskem": [
    14.80102,
    50.7028
  ],
  "Str\u00e1\u017enice": [
    17.3168,
    48.90102
  ],
  "Str\u00e1\u017en\u00e1": [
    17.13275,
    49.83104
  ],
  "Str\u00e1\u017eov": [
    13.24623,
    49.30326
  ],
  "Studenec": [
    15.54936,
    50.55344
  ],
  "Studen\u00e1": [
    15.28688,
    49.18516
  ],
  "Stud\u00e9nka": [
    18.07853,
    49.72342
  ],
  "St\u011bbo\u0159ice": [
    17.80547,
    49.93708
  ],
  "St\u011b\u017eery": [
    15.74831,
    50.21572
  ],
  "St\u0159elice": [
    16.50399,
    49.15221
  ],
  "St\u0159\u00edbro": [
    12.997,
    49.75565
  ],
  "St\u0159\u00ed\u017ekov": [
    14.49363,
    50.12674
  ],
  "Suchdol": [
    15.16651,
    49.95247
  ],
  "Suchdol nad Lu\u017enic\u00ed": [
    14.8772,
    48.89
  ],
  "Suchohrdly": [
    16.09471,
    48.86822
  ],
  "Such\u00e1 Loz": [
    17.71379,
    48.97001
  ],
  "Sudkov": [
    16.94516,
    49.91903
  ],
  "Sudom\u011b\u0159ice": [
    17.25676,
    48.86723
  ],
  "Su\u0161ice": [
    13.52018,
    49.23106
  ],
  "Svatava": [
    12.62524,
    50.19223
  ],
  "Sviadnov": [
    18.32762,
    49.68926
  ],
  "Svitavy": [
    16.46829,
    49.75594
  ],
  "Svit\u00e1vka": [
    16.59793,
    49.50178
  ],
  "Svoboda nad \u00dapou": [
    15.81648,
    50.62596
  ],
  "Svratka": [
    16.03214,
    49.71066
  ],
  "Sv\u011btl\u00e1 nad S\u00e1zavou": [
    15.40393,
    49.66801
  ],
  "S\u00e1zava": [
    14.89674,
    49.87164
  ],
  "Tachov": [
    12.63365,
    49.79528
  ],
  "Tanvald": [
    15.30585,
    50.73735
  ],
  "Tasovice": [
    16.15558,
    48.8361
  ],
  "Telnice": [
    16.71774,
    49.10187
  ],
  "Tel\u010d": [
    15.45275,
    49.18418
  ],
  "Teplice": [
    13.82451,
    50.6404
  ],
  "Teplice nad Metuj\u00ed": [
    16.17026,
    50.59332
  ],
  "Terez\u00edn": [
    14.15055,
    50.511
  ],
  "Te\u010dovice": [
    17.58733,
    49.22107
  ],
  "Tich\u00e1": [
    18.22148,
    49.56999
  ],
  "Ti\u0161ice": [
    14.55411,
    50.2698
  ],
  "Ti\u0161nov": [
    16.42438,
    49.34872
  ],
  "Tluma\u010dov": [
    17.49559,
    49.25351
  ],
  "Tlu\u010dn\u00e1": [
    13.23534,
    49.72425
  ],
  "Topoln\u00e1": [
    17.54434,
    49.12187
  ],
  "Tou\u017eim": [
    12.98506,
    50.06049
  ],
  "Tova\u010dov": [
    17.28795,
    49.43083
  ],
  "Traplice": [
    17.43622,
    49.13088
  ],
  "Trhov\u00e9 Sviny": [
    14.63924,
    48.84231
  ],
  "Trhov\u00fd \u0160t\u011bp\u00e1nov": [
    15.01356,
    49.71147
  ],
  "Trmice": [
    13.99449,
    50.64286
  ],
  "Trnava": [
    17.84191,
    49.29603
  ],
  "Trojanovice": [
    18.238,
    49.52039
  ],
  "Troubelice": [
    17.081,
    49.81731
  ],
  "Troubky": [
    17.34914,
    49.43215
  ],
  "Troubsko": [
    16.51078,
    49.16951
  ],
  "Trutnov": [
    15.9127,
    50.56101
  ],
  "Tr\u0161ice": [
    17.42483,
    49.54237
  ],
  "Tuchlovice": [
    13.99115,
    50.13803
  ],
  "Tuchom\u011b\u0159ice": [
    14.28218,
    50.13543
  ],
  "Tupesy": [
    17.36983,
    49.08427
  ],
  "Turnov": [
    15.15186,
    50.58356
  ],
  "Tvaro\u017en\u00e1": [
    16.77146,
    49.19177
  ],
  "Tvrdonice": [
    16.99446,
    48.76048
  ],
  "T\u00e1bor": [
    14.6578,
    49.41441
  ],
  "T\u00fdn nad Vltavou": [
    14.42057,
    49.2234
  ],
  "T\u00fdnec": [
    17.01322,
    48.77943
  ],
  "T\u00fdnec nad Labem": [
    15.35836,
    50.04202
  ],
  "T\u00fdnec nad S\u00e1zavou": [
    14.58983,
    49.83348
  ],
  "T\u00fdni\u0161t\u011b nad Orlic\u00ed": [
    16.0777,
    50.15136
  ],
  "T\u011b\u0161any": [
    16.77003,
    49.03956
  ],
  "T\u011b\u0161etice": [
    17.12607,
    49.59317
  ],
  "T\u0159ebechovice pod Orebem": [
    15.99223,
    50.20097
  ],
  "T\u0159ebenice": [
    13.99005,
    50.47632
  ],
  "T\u0159ebotov": [
    14.29127,
    49.97244
  ],
  "T\u0159ebo\u0148": [
    14.77065,
    49.00364
  ],
  "T\u0159eb\u00ed\u010d": [
    15.88166,
    49.21492
  ],
  "T\u0159emo\u0161nice": [
    15.58002,
    49.86912
  ],
  "T\u0159emo\u0161n\u00e1": [
    13.39499,
    49.81584
  ],
  "T\u0159e\u0161\u0165": [
    15.48211,
    49.29092
  ],
  "T\u0159inec": [
    18.67078,
    49.67763
  ],
  "Uhersk\u00e9 Hradi\u0161t\u011b": [
    17.45969,
    49.06975
  ],
  "Uhersk\u00fd Brod": [
    17.64715,
    49.02513
  ],
  "Uhersk\u00fd Ostroh": [
    17.38984,
    48.98556
  ],
  "Uhl\u00ed\u0159sk\u00e9 Janovice": [
    15.06481,
    49.88019
  ],
  "Unho\u0161\u0165": [
    14.13007,
    50.08535
  ],
  "Uni\u010dov": [
    17.12144,
    49.77092
  ],
  "Ur\u010dice": [
    17.07291,
    49.43045
  ],
  "Vacenovice": [
    17.17404,
    48.9451
  ],
  "Vacov": [
    13.72911,
    49.13686
  ],
  "Vala\u0161sk\u00e1 Byst\u0159ice": [
    18.10977,
    49.41507
  ],
  "Vala\u0161sk\u00e1 Polanka": [
    17.99667,
    49.26215
  ],
  "Vala\u0161sk\u00e9 Klobouky": [
    18.0076,
    49.14064
  ],
  "Vala\u0161sk\u00e9 Mezi\u0159\u00ed\u010d\u00ed": [
    17.97113,
    49.47181
  ],
  "Valdice": [
    15.38488,
    50.45501
  ],
  "Valtice": [
    16.75499,
    48.74069
  ],
  "Vamberk": [
    16.29067,
    50.11756
  ],
  "Varnsdorf": [
    14.61824,
    50.91154
  ],
  "Vejprnice": [
    13.27628,
    49.72988
  ],
  "Vejprty": [
    13.03212,
    50.49232
  ],
  "Velehrad": [
    17.39426,
    49.10543
  ],
  "Velem\u00edn": [
    13.97675,
    50.53898
  ],
  "Vele\u0161\u00edn": [
    14.46252,
    48.82949
  ],
  "Velim": [
    15.10711,
    50.05965
  ],
  "Velk\u00e1 Byst\u0159ice": [
    17.36544,
    49.5948
  ],
  "Velk\u00e1 B\u00edte\u0161": [
    16.22742,
    49.28838
  ],
  "Velk\u00e1 Dobr\u00e1": [
    14.0698,
    50.10964
  ],
  "Velk\u00e1 Hle\u010fsebe": [
    12.66763,
    49.96151
  ],
  "Velk\u00e1 Polom": [
    18.09331,
    49.86359
  ],
  "Velk\u00e1 nad Veli\u010dkou": [
    17.5206,
    48.88257
  ],
  "Velk\u00e9 B\u00edlovice": [
    16.89227,
    48.84929
  ],
  "Velk\u00e9 B\u0159ezno": [
    14.14174,
    50.6627
  ],
  "Velk\u00e9 Hamry": [
    15.31539,
    50.71373
  ],
  "Velk\u00e9 Heraltice": [
    17.72879,
    49.97493
  ],
  "Velk\u00e9 Ho\u0161tice": [
    17.9738,
    49.93609
  ],
  "Velk\u00e9 Karlovice": [
    18.28355,
    49.36064
  ],
  "Velk\u00e9 Losiny": [
    17.04058,
    50.03197
  ],
  "Velk\u00e9 Mezi\u0159\u00ed\u010d\u00ed": [
    16.01224,
    49.35522
  ],
  "Velk\u00e9 N\u011bm\u010dice": [
    16.67208,
    48.99168
  ],
  "Velk\u00e9 Opatovice": [
    16.67947,
    49.61237
  ],
  "Velk\u00e9 Pavlovice": [
    16.81605,
    48.90469
  ],
  "Velk\u00e9 Popovice": [
    14.63934,
    49.92252
  ],
  "Velk\u00e9 Po\u0159\u00ed\u010d\u00ed": [
    16.18931,
    50.46177
  ],
  "Velk\u00e9 P\u0159\u00edlepy": [
    14.31447,
    50.1605
  ],
  "Velk\u00e9 Svato\u0148ovice": [
    16.02853,
    50.53164
  ],
  "Velk\u00fd Beranov": [
    15.667,
    49.40504
  ],
  "Velk\u00fd Osek": [
    15.18629,
    50.09867
  ],
  "Velk\u00fd T\u00fdnec": [
    17.33359,
    49.54994
  ],
  "Velk\u00fd \u00dajezd": [
    17.48347,
    49.57858
  ],
  "Velk\u00fd \u0160enov": [
    14.37428,
    50.99078
  ],
  "Veltruby": [
    15.18454,
    50.07059
  ],
  "Veltrusy": [
    14.32857,
    50.27046
  ],
  "Velvary": [
    14.23616,
    50.28152
  ],
  "Vendryn\u011b": [
    18.71307,
    49.66662
  ],
  "Verne\u0159ice": [
    14.30114,
    50.66114
  ],
  "Vesel\u00ed nad Lu\u017enic\u00ed": [
    14.69734,
    49.1843
  ],
  "Vesel\u00ed nad Moravou": [
    17.37648,
    48.95363
  ],
  "Vestec": [
    14.50487,
    49.9805
  ],
  "Veversk\u00e1 B\u00edt\u00fd\u0161ka": [
    16.43686,
    49.27591
  ],
  "Ve\u0159ovice": [
    18.11425,
    49.53916
  ],
  "Vidnava": [
    17.18626,
    50.37234
  ],
  "Vid\u010de": [
    18.09473,
    49.44151
  ],
  "Vik\u00fd\u0159ovice": [
    17.01234,
    49.97792
  ],
  "Vil\u00e9mov": [
    15.38347,
    49.53578
  ],
  "Vimperk": [
    13.78286,
    49.05857
  ],
  "Vina\u0159ice": [
    14.09106,
    50.17585
  ],
  "Vini\u010dn\u00e9 \u0160umice": [
    16.82541,
    49.21358
  ],
  "Vint\u00ed\u0159ov": [
    12.71748,
    50.23382
  ],
  "Vizovice": [
    17.85455,
    49.22287
  ],
  "Vi\u0161\u0148ova": [
    15.02495,
    50.96663
  ],
  "Vi\u0161\u0148ov\u00e9": [
    16.15025,
    48.98241
  ],
  "Vlachovice": [
    17.94001,
    49.12377
  ],
  "Vlachovo B\u0159ez\u00ed": [
    13.95842,
    49.08135
  ],
  "Vladislav": [
    15.9883,
    49.21017
  ],
  "Vla\u0161im": [
    14.89881,
    49.70632
  ],
  "Vlko\u0161": [
    17.16356,
    48.9896
  ],
  "Vl\u010dnov": [
    17.58183,
    49.0099
  ],
  "Vnorovy": [
    17.3505,
    48.93096
  ],
  "Vod\u0148any": [
    14.17513,
    49.14789
  ],
  "Vojkovice": [
    16.6082,
    49.05138
  ],
  "Volary": [
    13.88657,
    48.90881
  ],
  "Volyn\u011b": [
    13.88624,
    49.16578
  ],
  "Votice": [
    14.63809,
    49.64013
  ],
  "Vracov": [
    17.211,
    48.97523
  ],
  "Vranovice": [
    16.6066,
    48.966
  ],
  "Vran\u00e9 nad Vltavou": [
    14.37706,
    49.93585
  ],
  "Vratimov": [
    18.31015,
    49.76995
  ],
  "Vrbice": [
    16.89779,
    48.91508
  ],
  "Vrbno pod Prad\u011bdem": [
    17.38316,
    50.12095
  ],
  "Vrbovec": [
    16.10061,
    48.79978
  ],
  "Vrb\u00e1tky": [
    17.19994,
    49.50805
  ],
  "Vrchlab\u00ed": [
    15.60937,
    50.62697
  ],
  "Vrdy": [
    15.47243,
    49.92153
  ],
  "Vroutek": [
    13.37986,
    50.17999
  ],
  "Vset\u00edn": [
    17.99619,
    49.33871
  ],
  "Vysok\u00e9 M\u00fdto": [
    16.16169,
    49.9532
  ],
  "Vysok\u00e9 nad Jizerou": [
    15.40152,
    50.68559
  ],
  "Vyso\u010dany": [
    14.51667,
    50.10938
  ],
  "Vy\u0161kov": [
    16.99897,
    49.27747
  ],
  "Vy\u0161\u0161\u00ed Brod": [
    14.31183,
    48.61598
  ],
  "V\u00e1clavovice": [
    18.3722,
    49.75531
  ],
  "V\u00e1penn\u00e1": [
    17.09762,
    50.28338
  ],
  "V\u00edtkov": [
    17.74941,
    49.77445
  ],
  "V\u010deln\u00e1": [
    14.45383,
    48.92373
  ],
  "V\u011brovany": [
    17.28795,
    49.46109
  ],
  "V\u011bt\u0159n\u00ed": [
    14.28616,
    48.77425
  ],
  "V\u0159esina": [
    18.12569,
    49.82418
  ],
  "V\u0161emina": [
    17.87682,
    49.281
  ],
  "V\u0161enory": [
    14.30392,
    49.92883
  ],
  "V\u0161eruby": [
    13.22943,
    49.84167
  ],
  "V\u0161estary": [
    15.75983,
    50.2566
  ],
  "V\u0161etaty": [
    14.59297,
    50.28187
  ],
  "Zabru\u0161any": [
    13.78748,
    50.60495
  ],
  "Zadn\u00ed Mostek": [
    15.69804,
    50.4967
  ],
  "Zaje\u010dov": [
    13.84072,
    49.77435
  ],
  "Zaje\u010d\u00ed": [
    16.76646,
    48.87295
  ],
  "Zast\u00e1vka": [
    16.3631,
    49.188
  ],
  "Za\u0161ov\u00e1": [
    18.04436,
    49.4741
  ],
  "Zbiroh": [
    13.77262,
    49.86024
  ],
  "Zborovice": [
    17.28464,
    49.24889
  ],
  "Zbraslav": [
    16.29415,
    49.22155
  ],
  "Zbraslavice": [
    15.18319,
    49.81179
  ],
  "Zb\u00fd\u0161ov": [
    16.34951,
    49.15524
  ],
  "Zb\u016fch": [
    13.22564,
    49.6784
  ],
  "Zdiby": [
    14.45118,
    50.16799
  ],
  "Zdice": [
    13.97747,
    49.91207
  ],
  "Zdounky": [
    17.31899,
    49.22771
  ],
  "Zd\u00edkov": [
    13.69738,
    49.08456
  ],
  "Zelene\u010d": [
    14.6607,
    50.13362
  ],
  "Zlat\u00e9 Hory": [
    17.39602,
    50.2638
  ],
  "Zlechov": [
    17.37938,
    49.07396
  ],
  "Zliv": [
    14.36613,
    49.06608
  ],
  "Zlonice": [
    14.09214,
    50.2875
  ],
  "Zl\u00edn": [
    17.67065,
    49.22645
  ],
  "Znojmo": [
    16.0488,
    48.8555
  ],
  "Zru\u010d nad S\u00e1zavou": [
    15.10606,
    49.7401
  ],
  "Zub\u0159\u00ed": [
    18.09249,
    49.46603
  ],
  "Zvole": [
    14.41769,
    49.93466
  ],
  "Z\u00e1b\u0159eh": [
    16.87223,
    49.8826
  ],
  "Z\u00e1horovice": [
    17.77922,
    49.02266
  ],
  "Z\u00e1kupy": [
    14.64522,
    50.68475
  ],
  "Z\u00e1smuky": [
    15.03058,
    49.9547
  ],
  "Z\u00e1tor": [
    17.59296,
    50.03413
  ],
  "\u00dadlice": [
    13.45738,
    50.4406
  ],
  "\u00dajezd": [
    17.9061,
    49.16809
  ],
  "\u00dananov": [
    16.06351,
    48.90082
  ],
  "\u00dapice": [
    16.01607,
    50.51237
  ],
  "\u00dasov": [
    17.01055,
    49.79831
  ],
  "\u00dast\u00ed nad Labem": [
    14.03227,
    50.6607
  ],
  "\u00dast\u00ed nad Orlic\u00ed": [
    16.39361,
    49.97387
  ],
  "\u00davaly": [
    14.7308,
    50.07394
  ],
  "\u00da\u0161t\u011bk": [
    14.34332,
    50.58474
  ],
  "\u010castolovice": [
    16.18128,
    50.1291
  ],
  "\u010ceb\u00edn": [
    16.47791,
    49.31324
  ],
  "\u010cechtice": [
    15.04824,
    49.62403
  ],
  "\u010cejkovice": [
    16.9423,
    48.90592
  ],
  "\u010cej\u010d": [
    16.96511,
    48.94653
  ],
  "\u010celadn\u00e1": [
    18.33759,
    49.54873
  ],
  "\u010celechovice na Han\u00e9": [
    17.09379,
    49.51626
  ],
  "\u010cel\u00e1kovice": [
    14.75005,
    50.16038
  ],
  "\u010cernilov": [
    15.92254,
    50.26265
  ],
  "\u010cernovice": [
    14.96089,
    49.37265
  ],
  "\u010cerno\u0161ice": [
    14.31979,
    49.96008
  ],
  "\u010cerno\u0161\u00edn": [
    12.88381,
    49.81613
  ],
  "\u010cerno\u017eice": [
    15.87403,
    50.31863
  ],
  "\u010cern\u00e1 Hora": [
    16.5814,
    49.41361
  ],
  "\u010cern\u00fd Most": [
    14.57974,
    50.10475
  ],
  "\u010cern\u010dice": [
    13.84521,
    50.36138
  ],
  "\u010cervenka": [
    17.07773,
    49.72068
  ],
  "\u010cerven\u00e1 Voda": [
    16.74268,
    50.04029
  ],
  "\u010cerven\u00e9 Pe\u010dky": [
    15.20856,
    49.97822
  ],
  "\u010cerven\u00fd Kostelec": [
    16.09289,
    50.47626
  ],
  "\u010cer\u010dany": [
    14.70299,
    49.85293
  ],
  "\u010cesk\u00e1 Kamenice": [
    14.41767,
    50.7978
  ],
  "\u010cesk\u00e1 L\u00edpa": [
    14.53764,
    50.68551
  ],
  "\u010cesk\u00e1 Skalice": [
    16.04276,
    50.39467
  ],
  "\u010cesk\u00e1 T\u0159ebov\u00e1": [
    16.44413,
    49.90436
  ],
  "\u010cesk\u00e1 Ves": [
    17.22805,
    50.25736
  ],
  "\u010cesk\u00e9 Bud\u011bjovice": [
    14.47434,
    48.97447
  ],
  "\u010cesk\u00e9 Mezi\u0159\u00ed\u010d\u00ed": [
    16.04428,
    50.2868
  ],
  "\u010cesk\u00e9 Velenice": [
    14.96368,
    48.76851
  ],
  "\u010cesk\u00fd Brod": [
    14.86081,
    50.0742
  ],
  "\u010cesk\u00fd Dub": [
    14.99617,
    50.66054
  ],
  "\u010cesk\u00fd Krumlov": [
    14.31521,
    48.81091
  ],
  "\u010cesk\u00fd Rudolec": [
    15.32437,
    49.06835
  ],
  "\u010cesk\u00fd T\u011b\u0161\u00edn": [
    18.62613,
    49.74613
  ],
  "\u010cimelice": [
    14.06922,
    49.46557
  ],
  "\u010ckyn\u011b": [
    13.82906,
    49.11503
  ],
  "\u010c\u00e1slav": [
    15.38972,
    49.91099
  ],
  "\u010c\u00ed\u017ekovice": [
    14.02839,
    50.48418
  ],
  "\u0158ehlovice": [
    13.95412,
    50.60712
  ],
  "\u0158epi\u0161t\u011b": [
    18.31707,
    49.73338
  ],
  "\u0158evnice": [
    14.23589,
    49.91395
  ],
  "\u0158evni\u010dov": [
    13.80823,
    50.18489
  ],
  "\u0158e\u010dany nad Labem": [
    15.47735,
    50.03589
  ],
  "\u0158e\u017e": [
    14.35733,
    50.17734
  ],
  "\u0158\u00ed\u010dany": [
    16.39362,
    49.21497
  ],
  "\u0160akvice": [
    16.71424,
    48.89746
  ],
  "\u0160anov": [
    16.37858,
    48.80089
  ],
  "\u0160ardice": [
    17.02812,
    48.96403
  ],
  "\u0160atov": [
    16.00992,
    48.79317
  ],
  "\u0160enov": [
    18.37607,
    49.79315
  ],
  "\u0160estajovice": [
    14.68013,
    50.10845
  ],
  "\u0160ev\u011bt\u00edn": [
    14.5722,
    49.10005
  ],
  "\u0160ilhe\u0159ovice": [
    18.27017,
    49.92602
  ],
  "\u0160itbo\u0159ice": [
    16.77975,
    49.01433
  ],
  "\u0160lapanice": [
    16.72731,
    49.16863
  ],
  "\u0160luknov": [
    14.45258,
    51.00369
  ],
  "\u0160pindler\u016fv Ml\u00fdn": [
    15.60944,
    50.72615
  ],
  "\u0160ternberk": [
    17.29889,
    49.73044
  ],
  "\u0160toky": [
    15.58863,
    49.50249
  ],
  "\u0160tramberk": [
    18.11741,
    49.59181
  ],
  "\u0160t\u00edtina": [
    18.01245,
    49.91487
  ],
  "\u0160t\u00edtn\u00e1 nad Vl\u00e1\u0159\u00ed": [
    17.98274,
    49.06881
  ],
  "\u0160t\u00edty": [
    16.76576,
    49.96122
  ],
  "\u0160t\u011bchovice": [
    14.40543,
    49.85109
  ],
  "\u0160t\u011bnovice": [
    13.39963,
    49.67051
  ],
  "\u0160t\u011bp\u00e1nkovice": [
    18.03741,
    49.95738
  ],
  "\u0160t\u011bp\u00e1nov": [
    17.22041,
    49.68404
  ],
  "\u0160t\u011bt\u00ed": [
    14.37421,
    50.45298
  ],
  "\u0160umice": [
    17.72205,
    49.02858
  ],
  "\u0160umperk": [
    16.97061,
    49.96528
  ],
  "\u0160vihov": [
    13.28417,
    49.48136
  ],
  "\u0160\u0165\u00e1hlavy": [
    13.50394,
    49.67555
  ],
  "\u017dab\u010dice": [
    16.60257,
    49.0116
  ],
  "\u017dacl\u00e9\u0159": [
    15.91063,
    50.66329
  ],
  "\u017damberk": [
    16.46738,
    50.08601
  ],
  "\u017dandov": [
    14.39623,
    50.71394
  ],
  "\u017datec": [
    13.54577,
    50.32717
  ],
  "\u017dd\u00e1nice": [
    17.02751,
    49.06729
  ],
  "\u017debr\u00e1k": [
    13.89735,
    49.87574
  ],
  "\u017deletava": [
    15.673,
    49.14187
  ],
  "\u017deleznice": [
    15.38459,
    50.47274
  ],
  "\u017delezn\u00e1 Ruda": [
    13.2352,
    49.13743
  ],
  "\u017delezn\u00fd Brod": [
    15.25408,
    50.64274
  ],
  "\u017dele\u0161ice": [
    16.58137,
    49.11689
  ],
  "\u017deliv": [
    15.22181,
    49.52984
  ],
  "\u017deravice": [
    17.23726,
    49.02288
  ],
  "\u017didlochovice": [
    16.61881,
    49.03952
  ],
  "\u017dihle": [
    13.37502,
    50.04491
  ],
  "\u017dirovnice": [
    15.18824,
    49.25318
  ],
  "\u017ditenice": [
    14.15665,
    50.55528
  ],
  "\u017di\u017eelice": [
    15.3932,
    50.13192
  ],
  "\u017dleby": [
    15.48853,
    49.88958
  ],
  "\u017dlutava": [
    17.49037,
    49.19976
  ],
  "\u017dlutice": [
    13.16297,
    50.09192
  ],
  "\u017dulov\u00e1": [
    17.09871,
    50.30933
  ],
  "\u017d\u010f\u00e1r": [
    15.08034,
    50.54366
  ],
  "\u017d\u010f\u00e1r nad S\u00e1zavou": [
    15.93924,
    49.56263
  ],
  "\u017d\u010f\u00e1r nad S\u00e1zavou Druhy": [
    15.93216,
    49.58726
  ]
}
